{
    "Version": "1.1",
    "Data": {
        "Source": "c:\\program files\\microsoft visual studio\\2022\\community\\vc\\tools\\msvc\\14.42.34433\\include\\format",
        "ProvidedModule": "",
        "ImportedModules": [],
        "ImportedHeaderUnits": [
            "c:\\program files\\microsoft visual studio\\2022\\community\\vc\\tools\\msvc\\14.42.34433\\include\\__msvc_format_ucd_tables.hpp",
            "c:\\program files\\microsoft visual studio\\2022\\community\\vc\\tools\\msvc\\14.42.34433\\include\\__msvc_formatter.hpp",
            "c:\\program files\\microsoft visual studio\\2022\\community\\vc\\tools\\msvc\\14.42.34433\\include\\__msvc_print.hpp",
            "c:\\program files\\microsoft visual studio\\2022\\community\\vc\\tools\\msvc\\14.42.34433\\include\\bit",
            "c:\\program files\\microsoft visual studio\\2022\\community\\vc\\tools\\msvc\\14.42.34433\\include\\charconv",
            "c:\\program files\\microsoft visual studio\\2022\\community\\vc\\tools\\msvc\\14.42.34433\\include\\concepts",
            "c:\\program files\\microsoft visual studio\\2022\\community\\vc\\tools\\msvc\\14.42.34433\\include\\cstdint",
            "c:\\program files\\microsoft visual studio\\2022\\community\\vc\\tools\\msvc\\14.42.34433\\include\\iterator",
            "c:\\program files\\microsoft visual studio\\2022\\community\\vc\\tools\\msvc\\14.42.34433\\include\\locale",
            "c:\\program files\\microsoft visual studio\\2022\\community\\vc\\tools\\msvc\\14.42.34433\\include\\stdexcept",
            "c:\\program files\\microsoft visual studio\\2022\\community\\vc\\tools\\msvc\\14.42.34433\\include\\xcall_once.h",
            "c:\\program files\\microsoft visual studio\\2022\\community\\vc\\tools\\msvc\\14.42.34433\\include\\xfilesystem_abi.h",
            "c:\\program files\\microsoft visual studio\\2022\\community\\vc\\tools\\msvc\\14.42.34433\\include\\xstring",
            "c:\\program files\\microsoft visual studio\\2022\\community\\vc\\tools\\msvc\\14.42.34433\\include\\xutility",
            "c:\\program files\\microsoft visual studio\\2022\\community\\vc\\tools\\msvc\\14.42.34433\\include\\tuple"
        ]
    }
}